README.rst
setup.py
layers.egg-info/PKG-INFO
layers.egg-info/SOURCES.txt
layers.egg-info/dependency_links.txt
layers.egg-info/entry_points.txt
layers.egg-info/requires.txt
layers.egg-info/top_level.txt
layers_util/__init__.py
layers_util/layers.py