Metadata-Version: 1.0
Name: layers
Version: 0.1.5
Summary: Layered source layouts for software development projects
Home-page: https://github.com/ribozz/layers
Author: Alex Rudakov
Author-email: ribozz+layers@gmail.com
License: UNKNOWN
Platform: UNKNOWN
